cobra_opt/__init__.py
cobra_opt/__main__.py
cobra_opt/ast_optimizer.py
cobra_opt/decompiler.py
cobra_opt-0.0.1.dist-info/LICENSE
cobra_opt-0.0.1.dist-info/METADATA
cobra_opt-0.0.1.dist-info/WHEEL
cobra_opt-0.0.1.dist-info/top_level.txt
cobra_opt-0.0.1.dist-info/RECORD
