Metadata-Version: 2.1
Name: cobra-opt
Version: 0.0.1
Summary: An optimizer for Python code.
Home-page: https://github.com/supremestdoggo/cobra
License: UNKNOWN
Platform: UNKNOWN
Classifier: Programming Language :: Python :: 3
Classifier: License :: OSI Approved :: MIT License
Classifier: Operating System :: OS Independent
Requires-Python: >=3.8
License-File: LICENSE
